derapi/__init__.py
derapi/client.py
derapi/errors.py
derapi/types.py
derapi/api/__init__.py
derapi/api/batteries/__init__.py
derapi/api/batteries/get_battery.py
derapi/api/batteries/get_battery_intervals.py
derapi/api/batteries/list_batteries.py
derapi/api/join/__init__.py
derapi/api/join/create_join_session.py
derapi/api/join/get_join_session_token.py
derapi/api/sites/__init__.py
derapi/api/sites/get_site.py
derapi/api/sites/get_site_battery_control.py
derapi/api/sites/get_site_battery_intervals.py
derapi/api/sites/get_site_solar_inverter_intervals.py
derapi/api/sites/list_sites.py
derapi/api/sites/put_site_battery_control.py
derapi/api/solar_inverters/__init__.py
derapi/api/solar_inverters/get_solar_inverter.py
derapi/api/solar_inverters/get_solar_inverter_intervals.py
derapi/api/solar_inverters/list_solar_inverters.py
derapi/api/vendor_credentials/__init__.py
derapi/api/vendor_credentials/create_vendor_credentials.py
derapi/api/vendor_credentials/delete_vendor_credentials.py
derapi/api/vendor_credentials/get_vendor_credentials.py
derapi/api/vendor_credentials/list_vendor_credentials.py
derapi/api/vendor_credentials/update_vendor_credentials.py
derapi/api/virtual/__init__.py
derapi/api/virtual/create_virtual_battery.py
derapi/api/virtual/create_virtual_site.py
derapi/api/virtual/create_virtual_solar_inverter.py
derapi/api/virtual/delete_virtual_battery.py
derapi/api/virtual/delete_virtual_site.py
derapi/api/virtual/delete_virtual_solar_inverter.py
derapi/api/virtual/get_virtual_battery.py
derapi/api/virtual/get_virtual_site.py
derapi/api/virtual/get_virtual_solar_inverter.py
derapi/api/virtual/list_virtual_batteries.py
derapi/api/virtual/list_virtual_sites.py
derapi/api/virtual/list_virtual_solar_inverters.py
derapi/models/__init__.py
derapi/models/battery.py
derapi/models/battery_interval.py
derapi/models/battery_mode.py
derapi/models/battery_recent_errors_error.py
derapi/models/battery_recent_errors_info.py
derapi/models/battery_recent_errors_start.py
derapi-0.1.2.dist-info/METADATA
derapi-0.1.2.dist-info/WHEEL
derapi-0.1.2.dist-info/licenses/LICENSE.txt
derapi-0.1.2.dist-info/RECORD
