Metadata-Version: 2.3
Name: derapi
Version: 0.1.2
Classifier: Development Status :: 4 - Beta
Classifier: Programming Language :: Python
Classifier: Programming Language :: Python :: 3.8
Classifier: Programming Language :: Python :: 3.9
Classifier: Programming Language :: Python :: 3.10
Classifier: Programming Language :: Python :: 3.11
Classifier: Programming Language :: Python :: 3.12
Classifier: Programming Language :: Python :: Implementation :: CPython
Classifier: Programming Language :: Python :: Implementation :: PyPy
Requires-Python: >=3.8
Requires-Dist: attrs>=21.3.0
Requires-Dist: httpx<0.28.0,>=0.20.0
Requires-Dist: python-dateutil==2.8.0
Provides-Extra: dev
Requires-Dist: pyright==v1.1.388; extra == 'dev'
